py_html_email/__init__.py
py_html_email/html_generic.html
py_html_email-0.0.2.dist-info/LICENSE
py_html_email-0.0.2.dist-info/METADATA
py_html_email-0.0.2.dist-info/WHEEL
py_html_email-0.0.2.dist-info/top_level.txt
py_html_email-0.0.2.dist-info/RECORD
