Metadata-Version: 2.1
Name: py_html_email
Version: 0.0.2
Summary: SMTP emailer to send HTML formated emails
Author-email: Tyler Anderson <tyleranderson827@gmail.com>
Project-URL: Homepage, https://github.com/ty-anderson/py_html_email
Classifier: Programming Language :: Python :: 3
Classifier: License :: OSI Approved :: MIT License
Classifier: Operating System :: OS Independent
Requires-Python: >=3.8
License-File: LICENSE
